[
  {
    "question_number": 1,
    "subject": "English Studies",
    "topic": "Vowel Sounds",
    "question_text": "Which of the following words contains the same vowel sound as the word 'bat' `/æ/`?",
    "options": {
      "a": "cat",
      "b": "car",
      "c": "cot",
      "d": "cut"
    },
    "correct_answer": "a",
    "difficulty": "Easy",
    "explanation": "The word 'bat' contains the short monophthong `/æ/`. Among the options, 'cat' also has the `/æ/` sound. 'Car' has `/a:/`, 'cot' has `/ɒ/`, and 'cut' has `/ʌ/`.",
    "section_id": null
  },
  {
    "question_number": 2,
    "subject": "English Studies",
    "topic": "Vowel Sounds",
    "question_text": "Identify the word that has the vowel sound `/ʊ/` as in 'book'.",
    "options": {
      "a": "fool",
      "b": "pool",
      "c": "pull",
      "d": "tool"
    },
    "correct_answer": "c",
    "difficulty": "Medium",
    "explanation": "The word 'book' is pronounced with the short vowel `/ʊ/`. 'Pull' also contains the `/ʊ/` sound, whereas 'fool', 'pool', and 'tool' contain the long vowel `/u:/` (moon).",
    "section_id": null
  },
  {
    "question_number": 3,
    "subject": "English Studies",
    "topic": "Vowel Sounds",
    "question_text": "Which of these words contains the long vowel sound `/i:/` as in 'beat'?",
    "options": {
      "a": "sit",
      "b": "seat",
      "c": "bit",
      "d": "fit"
    },
    "correct_answer": "b",
    "difficulty": "Easy",
    "explanation": "The word 'seat' contains the long vowel `/i:/`. The words 'sit', 'bit', and 'fit' all contain the short vowel `/i/`.",
    "section_id": null
  },
  {
    "question_number": 4,
    "subject": "English Studies",
    "topic": "Vowel Sounds",
    "question_text": "Find the odd word out based on the vowel sound.",
    "options": {
      "a": "hot",
      "b": "cot",
      "c": "pot",
      "d": "but"
    },
    "correct_answer": "d",
    "difficulty": "Easy",
    "explanation": "The words 'hot', 'cot', and 'pot' all share the `/ɒ/` (short 'o') sound. 'But' contains the `/ʌ/` sound (as in cup).",
    "section_id": null
  },
  {
    "question_number": 5,
    "subject": "English Studies",
    "topic": "Vowel Sounds",
    "question_text": "Which of the following words contains the vowel sound `/ɜ:/`?",
    "options": {
      "a": "bed",
      "b": "bird",
      "c": "bud",
      "d": "bad"
    },
    "correct_answer": "b",
    "difficulty": "Medium",
    "explanation": "The word 'bird' has the long vowel sound `/ɜ:/`. 'Bed' has `/e/`, 'bud' has `/ʌ/`, and 'bad' has `/æ/`.",
    "section_id": null
  },
  {
    "question_number": 6,
    "subject": "English Studies",
    "topic": "Diphthongs",
    "question_text": "Identify the word that contains the diphthong `/ei/` as found in 'day'.",
    "options": {
      "a": "say",
      "b": "sky",
      "c": "boy",
      "d": "cow"
    },
    "correct_answer": "a",
    "difficulty": "Easy",
    "explanation": "The word 'say' shares the `/ei/` diphthong with 'day'. 'Sky' has `/ai/`, 'boy' has `/ɔi/`, and 'cow' has `/au/`.",
    "section_id": null
  },
  {
    "question_number": 7,
    "subject": "English Studies",
    "topic": "Diphthongs",
    "question_text": "Which word corresponds to the diphthong `/iə/`?",
    "options": {
      "a": "care",
      "b": "tour",
      "c": "here",
      "d": "hair"
    },
    "correct_answer": "c",
    "difficulty": "Medium",
    "explanation": "The word 'here' contains the `/iə/` diphthong. 'Care' and 'hair' have `/eə/`, and 'tour' has `/ʊə/`.",
    "section_id": null
  },
  {
    "question_number": 8,
    "subject": "English Studies",
    "topic": "Diphthongs",
    "question_text": "Which of the following words contains the diphthong `/eə/`?",
    "options": {
      "a": "clear",
      "b": "care",
      "c": "poor",
      "d": "pie"
    },
    "correct_answer": "b",
    "difficulty": "Medium",
    "explanation": "The word 'care' is pronounced with the `/eə/` diphthong. 'Clear' is `/iə/`, 'poor' can be `/ʊə/` or `/ɔ:/`, and 'pie' is `/ai/`.",
    "section_id": null
  },
  {
    "question_number": 9,
    "subject": "English Studies",
    "topic": "Consonant Sounds",
    "question_text": "Which word serves as a minimal pair for the word 'fat' to contrast the `/f/` and `/v/` consonant sounds?",
    "options": {
      "a": "cat",
      "b": "mat",
      "c": "vat",
      "d": "pat"
    },
    "correct_answer": "c",
    "difficulty": "Easy",
    "explanation": "A minimal pair differs by only one phonological element. 'Fat' (`/fæt/`) and 'vat' (`/væt/`) contrast the unvoiced `/f/` and voiced `/v/` sounds.",
    "section_id": null
  },
  {
    "question_number": 10,
    "subject": "English Studies",
    "topic": "Consonant Sounds",
    "question_text": "Identify the minimal pair that contrasts the consonants `/p/` and `/b/` from the base word 'pin'.",
    "options": {
      "a": "tin",
      "b": "bin",
      "c": "sin",
      "d": "fin"
    },
    "correct_answer": "b",
    "difficulty": "Easy",
    "explanation": "'Pin' (`/pɪn/`) and 'bin' (`/bɪn/`) form a minimal pair highlighting the unvoiced `/p/` and voiced `/b/` plosive sounds.",
    "section_id": null
  },
  {
    "question_number": 11,
    "subject": "English Studies",
    "topic": "Consonant Sounds",
    "question_text": "Which of the following pairs is a minimal pair contrasting `/s/` and `/z/`?",
    "options": {
      "a": "sip and zip",
      "b": "sip and ship",
      "c": "zip and tip",
      "d": "sit and sat"
    },
    "correct_answer": "a",
    "difficulty": "Medium",
    "explanation": "The words 'sip' (`/sɪp/`) and 'zip' (`/zɪp/`) differ only in the initial consonant, perfectly contrasting the voiceless `/s/` and voiced `/z/`.",
    "section_id": null
  },
  {
    "question_number": 12,
    "subject": "English Studies",
    "topic": "Consonant Clusters",
    "question_text": "Which word correctly contains the `str-` consonant cluster?",
    "options": {
      "a": "scream",
      "b": "spring",
      "c": "struggle",
      "d": "splendid"
    },
    "correct_answer": "c",
    "difficulty": "Easy",
    "explanation": "The word 'struggle' begins with the `str-` cluster. 'Scream' uses `scr-`, 'spring' uses `spr-`, and 'splendid' uses `spl-`.",
    "section_id": null
  },
  {
    "question_number": 13,
    "subject": "English Studies",
    "topic": "Consonant Clusters",
    "question_text": "Identify the word that features the `spr-` consonant cluster at the beginning.",
    "options": {
      "a": "spray",
      "b": "stay",
      "c": "play",
      "d": "stray"
    },
    "correct_answer": "a",
    "difficulty": "Easy",
    "explanation": "The word 'spray' starts with the `spr-` cluster (`/spr/`). 'Stray' has `str-`, and 'play' has `pl-`.",
    "section_id": null
  },
  {
    "question_number": 14,
    "subject": "English Studies",
    "topic": "Consonant Clusters",
    "question_text": "Which word contains the `scr-` cluster?",
    "options": {
      "a": "stream",
      "b": "cream",
      "c": "scream",
      "d": "dream"
    },
    "correct_answer": "c",
    "difficulty": "Medium",
    "explanation": "The word 'scream' starts with the three-consonant cluster `scr-` (`/skr/`).",
    "section_id": null
  },
  {
    "question_number": 15,
    "subject": "English Studies",
    "topic": "Consonant Clusters",
    "question_text": "Which of the following contains the consonant cluster `bl-`?",
    "options": {
      "a": "black",
      "b": "back",
      "c": "brash",
      "d": "lack"
    },
    "correct_answer": "a",
    "difficulty": "Easy",
    "explanation": "The word 'black' features the initial consonant cluster `bl-` (`/bl/`).",
    "section_id": null
  },
  {
    "question_number": 16,
    "subject": "English Studies",
    "topic": "Word Stress",
    "question_text": "Identify the word stress on 'present' when it is used as a Noun (e.g., 'I bought a present').",
    "options": {
      "a": "PRE-sent (First syllable is stressed)",
      "b": "pre-SENT (Second syllable is stressed)",
      "c": "pre-sent (Neither syllable is stressed)",
      "d": "PRE-SENT (Both syllables are equally stressed)"
    },
    "correct_answer": "a",
    "difficulty": "Medium",
    "explanation": "In English, two-syllable words that can be both nouns and verbs usually have the stress on the first syllable for the noun ('PRE-sent') and the second syllable for the verb ('pre-SENT').",
    "section_id": null
  },
  {
    "question_number": 17,
    "subject": "English Studies",
    "topic": "Word Stress",
    "question_text": "Where is the primary stress located in the word 'respect'?",
    "options": {
      "a": "First syllable (RE-spect)",
      "b": "Second syllable (re-SPECT)",
      "c": "Both syllables (RE-SPECT)",
      "d": "No noticeable stress"
    },
    "correct_answer": "b",
    "difficulty": "Medium",
    "explanation": "The word 'respect' (whether a noun or a verb) carries primary stress on the second syllable: re-SPECT.",
    "section_id": null
  },
  {
    "question_number": 18,
    "subject": "English Studies",
    "topic": "Sentence Stress",
    "question_text": "In English sentence stress, which categories of words are typically stressed?",
    "options": {
      "a": "Function words (e.g., articles, prepositions)",
      "b": "Content words (e.g., nouns, principal verbs)",
      "c": "Conjunctions only",
      "d": "Pronouns only"
    },
    "correct_answer": "b",
    "difficulty": "Medium",
    "explanation": "In spoken English, content words (nouns, main verbs, adjectives, adverbs) carry the meaning and are naturally stressed, whereas function words are typically unstressed.",
    "section_id": null
  },
  {
    "question_number": 19,
    "subject": "English Studies",
    "topic": "Intonation",
    "question_text": "What type of intonation pattern is typically used for a Yes/No question (e.g., 'Are you coming with us?')?",
    "options": {
      "a": "Falling intonation (↘)",
      "b": "Rising intonation (↗)",
      "c": "Fall-Rise intonation (↘↗)",
      "d": "Flat intonation"
    },
    "correct_answer": "b",
    "difficulty": "Medium",
    "explanation": "Yes/No questions usually end with a rising intonation pattern to indicate that a response is required.",
    "section_id": null
  },
  {
    "question_number": 20,
    "subject": "English Studies",
    "topic": "Intonation",
    "question_text": "Which intonation pattern is generally applied to standard statements or commands (e.g., 'Close the door.')?",
    "options": {
      "a": "Falling intonation (↘)",
      "b": "Rising intonation (↗)",
      "c": "Fall-Rise intonation (↘↗)",
      "d": "Flat intonation"
    },
    "correct_answer": "a",
    "difficulty": "Easy",
    "explanation": "Standard declarative sentences and definitive commands end with a falling intonation.",
    "section_id": null
  },
  {
    "question_number": 21,
    "subject": "English Studies",
    "topic": "Intonation",
    "question_text": "A Fall-Rise (↘↗) intonation pattern is most often used to express:",
    "options": {
      "a": "Absolute certainty or strong command",
      "b": "A direct Yes/No inquiry",
      "c": "Doubt, hesitation, or a partial agreement",
      "d": "A factual, indisputable statement"
    },
    "correct_answer": "c",
    "difficulty": "Hard",
    "explanation": "The Fall-Rise intonation indicates that the speaker is hesitating, doubtful, or has more to add (e.g., 'She is smart, but...').",
    "section_id": null
  },
  {
    "question_number": 22,
    "subject": "English Studies",
    "topic": "Rhythm",
    "question_text": "The rhythm of the spoken English language is best described as:",
    "options": {
      "a": "Syllable-timed",
      "b": "Stress-timed",
      "c": "Mora-timed",
      "d": "Pitch-timed"
    },
    "correct_answer": "b",
    "difficulty": "Medium",
    "explanation": "English is a stress-timed language, meaning the intervals between stressed syllables are roughly equal, causing unstressed syllables to be compressed or spoken more rapidly.",
    "section_id": null
  },
  {
    "question_number": 23,
    "subject": "English Studies",
    "topic": "Oral Comprehension",
    "question_text": "Read the following prompt and answer the question: \n'Mr. Okafor always demands a receipt for every purchase made for the school, recording each item neatly in a ledger so that no money goes missing.'\nWhat concept is best demonstrated by Mr. Okafor's actions?",
    "options": {
      "a": "Child labour",
      "b": "Accountability",
      "c": "Family bonding",
      "d": "Traffic control"
    },
    "correct_answer": "b",
    "difficulty": "Easy",
    "explanation": "Mr. Okafor's careful recording of purchases and demanding of receipts demonstrates accountability—taking responsibility for the use of funds.",
    "section_id": null
  },
  {
    "question_number": 24,
    "subject": "English Studies",
    "topic": "Oral Comprehension",
    "question_text": "![Placeholder image showing a busy Nigerian highway with moving vehicles](https://via.placeholder.com/800x400?text=Busy+Highway+Traffic)\n\n'The line of vehicles stretched for miles, not moving for over three hours, leading to loud blaring of horns and frustrated drivers.'\nThis scenario is an example of:",
    "options": {
      "a": "A peaceful street",
      "b": "Pedestrian safety",
      "c": "Traffic congestion",
      "d": "Child labour"
    },
    "correct_answer": "c",
    "difficulty": "Easy",
    "explanation": "Vehicles standing still for hours with frustrated drivers is a classic description of severe traffic congestion or a traffic jam.",
    "section_id": null
  },
  {
    "question_number": 25,
    "subject": "English Studies",
    "topic": "Oral Comprehension",
    "question_text": "Listen/Read: 'Instead of being in the classroom at 9:00 AM, twelve-year-old Amina was seen weaving through moving cars on the highway, balancing a tray of cold drinks on her head to sell.'\nWhat societal issue does this prompt highlight?",
    "options": {
      "a": "Accountability",
      "b": "Traffic rules",
      "c": "Child labour",
      "d": "Disease prevention"
    },
    "correct_answer": "c",
    "difficulty": "Easy",
    "explanation": "A young child working on the streets during school hours to earn money is a direct example of child labour.",
    "section_id": null
  },
  {
    "question_number": 26,
    "subject": "English Studies",
    "topic": "Oral Comprehension",
    "question_text": "Read the prompt: 'To protect his family from the recent cholera outbreak, Mr. Bello insisted that all drinking water be boiled and that everyone wash their hands with soap before meals.'\nWhat is the central topic of this prompt?",
    "options": {
      "a": "Preventing diseases",
      "b": "Road safety",
      "c": "Accountability in government",
      "d": "Family leisure time"
    },
    "correct_answer": "a",
    "difficulty": "Easy",
    "explanation": "Boiling water and washing hands to stop cholera spread directly relates to preventing diseases through proper hygiene.",
    "section_id": null
  },
  {
    "question_number": 27,
    "subject": "English Studies",
    "topic": "Oral Comprehension",
    "question_text": "Read the following: 'Every Sunday afternoon, the parents and their three children sit down together without their phones to discuss their weekly challenges and play board games.'\nWhat does this scenario best represent?",
    "options": {
      "a": "Family unity and communication",
      "b": "Financial accountability",
      "c": "Public health awareness",
      "d": "The dangers of child labour"
    },
    "correct_answer": "a",
    "difficulty": "Easy",
    "explanation": "A family setting aside time specifically to bond, converse, and play together clearly represents family unity and communication.",
    "section_id": null
  },
  {
    "question_number": 28,
    "subject": "English Studies",
    "topic": "Vowel Sounds",
    "question_text": "Identify the word that contains the vowel sound `/ʌ/` as in 'cup'.",
    "options": {
      "a": "cop",
      "b": "cap",
      "c": "coop",
      "d": "hut"
    },
    "correct_answer": "d",
    "difficulty": "Easy",
    "explanation": "The word 'hut' uses the `/ʌ/` sound (short 'u'), exactly like 'cup'. 'Cop' uses `/ɒ/`, 'cap' uses `/æ/`, and 'coop' uses `/u:/`.",
    "section_id": null
  },
  {
    "question_number": 29,
    "subject": "English Studies",
    "topic": "Consonant Sounds",
    "question_text": "Identify the minimal pair that contrasts the consonants `/k/` and `/g/`.",
    "options": {
      "a": "coat and goat",
      "b": "cat and bat",
      "c": "get and let",
      "d": "car and bar"
    },
    "correct_answer": "a",
    "difficulty": "Medium",
    "explanation": "The words 'coat' (`/kəʊt/`) and 'goat' (`/gəʊt/`) are identical except for their initial unvoiced `/k/` and voiced `/g/` consonant sounds.",
    "section_id": null
  },
  {
    "question_number": 30,
    "subject": "English Studies",
    "topic": "Sentence Stress",
    "question_text": "In the sentence, 'I MUST GO to the STORE,' which words are the stressed content words?",
    "options": {
      "a": "I, to, the",
      "b": "MUST, GO, STORE",
      "c": "GO, STORE",
      "d": "I, STORE"
    },
    "correct_answer": "c",
    "difficulty": "Hard",
    "explanation": "Generally, content words (verbs like 'go', nouns like 'store') carry the stress. Modals (must) and pronouns/prepositions (I, to, the) are usually unstressed in natural speech, though 'must' can be stressed for emphasis. 'GO' and 'STORE' are the primary stressed content words.",
    "section_id": null
  },
  {
    "question_number": 31,
    "subject": "English Studies",
    "topic": "Vowel Sounds",
    "question_text": "Which of the following words contains the long vowel sound `/a:/` as in the word 'car'?",
    "options": {
      "a": "cat",
      "b": "part",
      "c": "cot",
      "d": "pet"
    },
    "correct_answer": "b",
    "difficulty": "Easy",
    "explanation": "The word 'part' shares the long monophthong `/a:/` with the word 'car'. 'Cat' has `/æ/`, 'cot' has `/ɒ/`, and 'pet' has `/e/`.",
    "section_id": null
  },
  {
    "question_number": 32,
    "subject": "English Studies",
    "topic": "Vowel Sounds",
    "question_text": "Identify the word that uses the vowel sound `/ɔ:/` like in the word 'law'.",
    "options": {
      "a": "saw",
      "b": "cow",
      "c": "so",
      "d": "now"
    },
    "correct_answer": "a",
    "difficulty": "Easy",
    "explanation": "The word 'saw' contains the long vowel `/ɔ:/`. 'Cow' and 'now' contain the diphthong `/au/`, while 'so' contains `/əʊ/`.",
    "section_id": null
  },
  {
    "question_number": 33,
    "subject": "English Studies",
    "topic": "Vowel Sounds",
    "question_text": "Which of the following words begins with the schwa sound `/ə/` as in 'about'?",
    "options": {
      "a": "apple",
      "b": "away",
      "c": "aunt",
      "d": "arch"
    },
    "correct_answer": "b",
    "difficulty": "Medium",
    "explanation": "The word 'away' begins with the unstressed schwa sound `/ə/`. 'Apple' begins with `/æ/`, while 'aunt' and 'arch' begin with `/a:/`.",
    "section_id": null
  },
  {
    "question_number": 34,
    "subject": "English Studies",
    "topic": "Vowel Sounds",
    "question_text": "Find the word that contains the short vowel sound `/e/` as found in 'bed'.",
    "options": {
      "a": "head",
      "b": "hard",
      "c": "hide",
      "d": "heed"
    },
    "correct_answer": "a",
    "difficulty": "Easy",
    "explanation": "Despite its spelling, the word 'head' is pronounced with the short vowel `/e/`. 'Hard' is `/a:/`, 'hide' is `/ai/`, and 'heed' is `/i:/`.",
    "section_id": null
  },
  {
    "question_number": 35,
    "subject": "English Studies",
    "topic": "Vowel Sounds",
    "question_text": "Which word has the short vowel sound `/i/` as in 'sit'?",
    "options": {
      "a": "sight",
      "b": "site",
      "c": "hit",
      "d": "heat"
    },
    "correct_answer": "c",
    "difficulty": "Easy",
    "explanation": "The word 'hit' features the short vowel `/i/`. 'Heat' uses the long `/i:/`, and 'sight'/'site' use the diphthong `/ai/`.",
    "section_id": null
  },
  {
    "question_number": 36,
    "subject": "English Studies",
    "topic": "Diphthongs",
    "question_text": "Identify the word that contains the diphthong `/au/` as heard in 'cow'.",
    "options": {
      "a": "low",
      "b": "show",
      "c": "loud",
      "d": "law"
    },
    "correct_answer": "c",
    "difficulty": "Medium",
    "explanation": "The word 'loud' contains the `/au/` diphthong. 'Low' and 'show' use `/əʊ/`, and 'law' uses `/ɔ:/`.",
    "section_id": null
  },
  {
    "question_number": 37,
    "subject": "English Studies",
    "topic": "Diphthongs",
    "question_text": "Which of these words contains the diphthong `/ɔi/` found in the word 'boy'?",
    "options": {
      "a": "buy",
      "b": "boil",
      "c": "bow",
      "d": "ball"
    },
    "correct_answer": "b",
    "difficulty": "Easy",
    "explanation": "The word 'boil' features the `/ɔi/` diphthong. 'Buy' uses `/ai/`, 'bow' can be `/au/` or `/əʊ/`, and 'ball' uses `/ɔ:/`.",
    "section_id": null
  },
  {
    "question_number": 38,
    "subject": "English Studies",
    "topic": "Diphthongs",
    "question_text": "Which of the following words contains the diphthong `/ai/` like in the word 'my'?",
    "options": {
      "a": "may",
      "b": "me",
      "c": "sky",
      "d": "see"
    },
    "correct_answer": "c",
    "difficulty": "Easy",
    "explanation": "The word 'sky' contains the `/ai/` sound. 'May' has `/ei/`, while 'me' and 'see' contain `/i:/`.",
    "section_id": null
  },
  {
    "question_number": 39,
    "subject": "English Studies",
    "topic": "Diphthongs",
    "question_text": "Select the word that represents the `/ʊə/` sound as seen in 'tour'.",
    "options": {
      "a": "pure",
      "b": "pour",
      "c": "pear",
      "d": "purr"
    },
    "correct_answer": "a",
    "difficulty": "Hard",
    "explanation": "The word 'pure' commonly employs the `/ʊə/` diphthong (often preceded by /j/). 'Pour' is usually `/ɔ:/`, 'pear' is `/eə/`, and 'purr' is `/ɜ:/`.",
    "section_id": null
  },
  {
    "question_number": 40,
    "subject": "English Studies",
    "topic": "Consonant Sounds",
    "question_text": "Identify the minimal pair that properly contrasts the alveolar plosives `/t/` and `/d/`.",
    "options": {
      "a": "tin and pin",
      "b": "tip and dip",
      "c": "dip and zip",
      "d": "tap and cap"
    },
    "correct_answer": "b",
    "difficulty": "Easy",
    "explanation": "The words 'tip' and 'dip' differ only in the initial consonants `/t/` (voiceless) and `/d/` (voiced), making them a minimal pair for these sounds.",
    "section_id": null
  },
  {
    "question_number": 41,
    "subject": "English Studies",
    "topic": "Consonant Sounds",
    "question_text": "Which of the following creates a minimal pair contrasting `/f/` and `/v/`?",
    "options": {
      "a": "feel and peel",
      "b": "fan and van",
      "c": "vest and best",
      "d": "fat and cat"
    },
    "correct_answer": "b",
    "difficulty": "Easy",
    "explanation": "The words 'fan' and 'van' contrast the unvoiced labiodental fricative `/f/` and its voiced counterpart `/v/`.",
    "section_id": null
  },
  {
    "question_number": 42,
    "subject": "English Studies",
    "topic": "Consonant Clusters",
    "question_text": "Which word contains the initial consonant cluster `gr-`?",
    "options": {
      "a": "glare",
      "b": "great",
      "c": "gate",
      "d": "rate"
    },
    "correct_answer": "b",
    "difficulty": "Easy",
    "explanation": "The word 'great' starts with the `gr-` cluster (`/gr/`). 'Glare' begins with `gl-`.",
    "section_id": null
  },
  {
    "question_number": 43,
    "subject": "English Studies",
    "topic": "Consonant Clusters",
    "question_text": "Identify the word that features the `tr-` consonant cluster.",
    "options": {
      "a": "train",
      "b": "chain",
      "c": "rain",
      "d": "stain"
    },
    "correct_answer": "a",
    "difficulty": "Easy",
    "explanation": "The word 'train' contains the initial `tr-` cluster. 'Chain' uses a single affricate `/tʃ/`, 'stain' uses `st-`.",
    "section_id": null
  },
  {
    "question_number": 44,
    "subject": "English Studies",
    "topic": "Consonant Clusters",
    "question_text": "Which word starts with the consonant cluster `pl-`?",
    "options": {
      "a": "pray",
      "b": "play",
      "c": "pay",
      "d": "lay"
    },
    "correct_answer": "b",
    "difficulty": "Easy",
    "explanation": "The word 'play' begins with the `pl-` consonant cluster.",
    "section_id": null
  },
  {
    "question_number": 45,
    "subject": "English Studies",
    "topic": "Consonant Clusters",
    "question_text": "Select the word that correctly contains the consonant cluster `bl-`.",
    "options": {
      "a": "bake",
      "b": "brake",
      "c": "blank",
      "d": "bank"
    },
    "correct_answer": "c",
    "difficulty": "Medium",
    "explanation": "The word 'blank' begins with the cluster `bl-`. 'Brake' uses the `br-` cluster.",
    "section_id": null
  },
  {
    "question_number": 46,
    "subject": "English Studies",
    "topic": "Word Stress",
    "question_text": "When the word 'record' is used as a Noun (e.g., 'He broke the world record'), which syllable receives the primary stress?",
    "options": {
      "a": "First syllable (RE-cord)",
      "b": "Second syllable (re-CORD)",
      "c": "Both syllables (RE-CORD)",
      "d": "Neither syllable"
    },
    "correct_answer": "a",
    "difficulty": "Medium",
    "explanation": "As a noun, the stress falls on the first syllable (RE-cord). When used as a verb (e.g., 'Please record this'), the stress falls on the second syllable (re-CORD).",
    "section_id": null
  },
  {
    "question_number": 47,
    "subject": "English Studies",
    "topic": "Word Stress",
    "question_text": "Where is the stress placed on the word 'project' when it acts as a Verb (e.g., 'The light will project onto the wall')?",
    "options": {
      "a": "PRO-ject (First syllable)",
      "b": "pro-JECT (Second syllable)",
      "c": "PRO-JECT (Equal stress)",
      "d": "It depends on the dialect"
    },
    "correct_answer": "b",
    "difficulty": "Medium",
    "explanation": "For the verb form, the primary stress lands on the second syllable (pro-JECT). The noun form has the stress on the first syllable (PRO-ject).",
    "section_id": null
  },
  {
    "question_number": 48,
    "subject": "English Studies",
    "topic": "Sentence Stress",
    "question_text": "In standard English sentence stress, words like 'a', 'the', 'and', or 'of' are considered:",
    "options": {
      "a": "Content words and are heavily stressed",
      "b": "Function words and are heavily stressed",
      "c": "Content words and are normally unstressed",
      "d": "Function words and are normally unstressed"
    },
    "correct_answer": "d",
    "difficulty": "Easy",
    "explanation": "Articles, conjunctions, and prepositions are function words. In the natural rhythm of English speech, they are normally unstressed.",
    "section_id": null
  },
  {
    "question_number": 49,
    "subject": "English Studies",
    "topic": "Intonation",
    "question_text": "Which intonation mark applies correctly to the command: 'Sit down immediately!'?",
    "options": {
      "a": "Rising (↗)",
      "b": "Falling (↘)",
      "c": "Fall-Rise (↘↗)",
      "d": "Level (-)"
    },
    "correct_answer": "b",
    "difficulty": "Medium",
    "explanation": "Commands and strong declarative statements naturally take a falling intonation (↘) in English.",
    "section_id": null
  },
  {
    "question_number": 50,
    "subject": "English Studies",
    "topic": "Intonation",
    "question_text": "Listen/Read: 'Did you complete your homework?'\nWhich intonation pattern should be applied at the end of this sentence?",
    "options": {
      "a": "Falling intonation (↘)",
      "b": "Fall-Rise intonation (↘↗)",
      "c": "Rising intonation (↗)",
      "d": "No intonation change"
    },
    "correct_answer": "c",
    "difficulty": "Medium",
    "explanation": "Because it is a Yes/No question, the voice generally goes up at the end, creating a rising intonation pattern (↗).",
    "section_id": null
  },
  {
    "question_number": 51,
    "subject": "English Studies",
    "topic": "Intonation",
    "question_text": "If a speaker responds with 'I might be able to help...', with a tone indicating hesitation and doubt, the most likely intonation pattern is:",
    "options": {
      "a": "Falling (↘)",
      "b": "Rising (↗)",
      "c": "Fall-Rise (↘↗)",
      "d": "High flat (—)"
    },
    "correct_answer": "c",
    "difficulty": "Hard",
    "explanation": "A Fall-Rise intonation (↘↗) is a key indicator of hesitation, doubt, or suggesting a 'but...' implicitly.",
    "section_id": null
  },
  {
    "question_number": 52,
    "subject": "English Studies",
    "topic": "Rhythm",
    "question_text": "What does it mean to say that English is a 'stress-timed' language?",
    "options": {
      "a": "Every syllable takes the exact same amount of time to say.",
      "b": "The duration between stressed syllables is roughly equal.",
      "c": "Only nouns are ever spoken out loud.",
      "d": "Sentences end on a specific pitch regardless of length."
    },
    "correct_answer": "b",
    "difficulty": "Hard",
    "explanation": "In a stress-timed language like English, the time it takes to go from one stressed syllable to the next is approximately the same, causing unstressed syllables in between to be spoken quicker.",
    "section_id": null
  },
  {
    "question_number": 53,
    "subject": "English Studies",
    "topic": "Oral Comprehension",
    "question_text": "![Placeholder: An image of a family gathering in a living room](https://via.placeholder.com/800x400?text=Family+Gathering)\n\nPrompt: 'After dinner, Mr. and Mrs. Adebayo and their children gathered in the parlor. They discussed the kids' schoolwork, told funny stories, and advised the eldest on picking a career.'\nWhat is the dominant theme of this passage?",
    "options": {
      "a": "Child labour",
      "b": "Disease prevention",
      "c": "Traffic management",
      "d": "Family bonding and guidance"
    },
    "correct_answer": "d",
    "difficulty": "Easy",
    "explanation": "The passage clearly describes a family coming together to converse, joke, and offer guidance, highlighting family bonding.",
    "section_id": null
  },
  {
    "question_number": 54,
    "subject": "English Studies",
    "topic": "Oral Comprehension",
    "question_text": "Prompt: 'The government official held a town hall meeting. She publicly showed the budget, exactly how much money was spent on the new hospital, and answered all questions regarding the finances.'\nWhich concept is the official demonstrating?",
    "options": {
      "a": "Hesitation",
      "b": "Accountability",
      "c": "Stress-timing",
      "d": "Intonation"
    },
    "correct_answer": "b",
    "difficulty": "Medium",
    "explanation": "By openly showing how money was spent and answering questions, the official is taking responsibility and showing financial accountability.",
    "section_id": null
  },
  {
    "question_number": 55,
    "subject": "English Studies",
    "topic": "Oral Comprehension",
    "question_text": "Prompt: 'To stop the spread of malaria, the community organized a massive clean-up to empty all stagnant water where mosquitoes breed, and distributed treated nets to every household.'\nWhat is the main topic of this scenario?",
    "options": {
      "a": "Diseases and public health",
      "b": "Managing road traffic",
      "c": "Financial accountability",
      "d": "Word stress in English"
    },
    "correct_answer": "a",
    "difficulty": "Easy",
    "explanation": "Fighting mosquito breeding sites and giving out nets are direct actions taken to prevent malaria, a disease. Thus, the topic is diseases/public health.",
    "section_id": null
  },
  {
    "question_number": 56,
    "subject": "English Studies",
    "topic": "Oral Comprehension",
    "question_text": "Prompt: 'Ten-year-old Musa should have been learning mathematics, but instead, his uncle had him carrying heavy blocks at a construction site from dawn to dusk for minimal pay.'\nThis scenario is an example of:",
    "options": {
      "a": "Family tradition",
      "b": "Child labour",
      "c": "Physical education",
      "d": "Accountability"
    },
    "correct_answer": "b",
    "difficulty": "Easy",
    "explanation": "Making a ten-year-old do heavy, paid manual labor at a construction site instead of attending school is a stark example of child labour.",
    "section_id": null
  },
  {
    "question_number": 57,
    "subject": "English Studies",
    "topic": "Consonant Sounds",
    "question_text": "Identify the minimal pair contrasting `/s/` and `/z/`.",
    "options": {
      "a": "sea and she",
      "b": "rice and rise",
      "c": "zinc and sink",
      "d": "both b and c"
    },
    "correct_answer": "d",
    "difficulty": "Hard",
    "explanation": "Both 'rice' (`/s/`) vs 'rise' (`/z/`) and 'sink' (`/s/`) vs 'zinc' (`/z/`) form valid minimal pairs contrasting the unvoiced `/s/` and voiced `/z/` sounds.",
    "section_id": null
  },
  {
    "question_number": 58,
    "subject": "English Studies",
    "topic": "Consonant Sounds",
    "question_text": "Which pair of words forms a minimal pair contrasting `/p/` and `/b/`?",
    "options": {
      "a": "rope and robe",
      "b": "pit and bit",
      "c": "cap and cab",
      "d": "all of the above"
    },
    "correct_answer": "d",
    "difficulty": "Medium",
    "explanation": "All options demonstrate the `/p/` and `/b/` contrast. 'Rope'/'robe' (final), 'pit'/'bit' (initial), and 'cap'/'cab' (final) differ only by the unvoiced/voiced bilabial plosive.",
    "section_id": null
  },
  {
    "question_number": 59,
    "subject": "English Studies",
    "topic": "Consonant Clusters",
    "question_text": "Which of the following sentences contains a word with the `scr-` cluster?",
    "options": {
      "a": "The cat will scratch the furniture.",
      "b": "We will scroll through the pages.",
      "c": "He heard a loud scream.",
      "d": "All of the above"
    },
    "correct_answer": "d",
    "difficulty": "Medium",
    "explanation": "The words 'scratch', 'scroll', and 'scream' all begin with the `scr-` consonant cluster (`/skr/`).",
    "section_id": null
  },
  {
    "question_number": 60,
    "subject": "English Studies",
    "topic": "Oral Comprehension",
    "question_text": "Prompt: 'At the major intersection, the traffic lights broke down, and there were no wardens on duty. Cars blocked one another from all four directions, resulting in total gridlock.'\nThis describes a problem relating to:",
    "options": {
      "a": "Family affairs",
      "b": "Child labour",
      "c": "Traffic",
      "d": "Disease prevention"
    },
    "correct_answer": "c",
    "difficulty": "Easy",
    "explanation": "A gridlock caused by broken traffic lights and blocking cars is completely about a traffic problem.",
    "section_id": null
  }
]