{
  "generatedAt": "2026-07-22T13:25:44.854Z",
  "totalFiles": 21,
  "totalQuestions": 23555,
  "files": [
    {
      "file": "pyq/classified/jee_classified.json",
      "count": 300
    },
    {
      "file": "pyq/jee_advanced/JEE_Advanced_2020.json",
      "count": 33
    },
    {
      "file": "pyq/jee_advanced/JEE_Advanced_2021.json",
      "count": 32
    },
    {
      "file": "pyq/jee_advanced/JEE_Advanced_2022.json",
      "count": 25
    },
    {
      "file": "pyq/jee_advanced/JEE_Advanced_2023.json",
      "count": 33
    },
    {
      "file": "pyq/jee_advanced/JEE_Advanced_2024.json",
      "count": 32
    },
    {
      "file": "pyq/jee_advanced/JEE_Advanced_2025.json",
      "count": 29
    },
    {
      "file": "pyq/jee_main/jeeMain_2025_22Jan_shift1.json",
      "count": 75
    },
    {
      "file": "pyq/jee_main/jeeMain_2025_22Jan_shift2.json",
      "count": 75
    },
    {
      "file": "pyq/jee_main/jeeMain_2026_02April_shift1.json",
      "count": 75
    },
    {
      "file": "pyq/jee_main/jeeMain_2026_02April_shift2.json",
      "count": 75
    },
    {
      "file": "pyq/jee_main/jeeMain_2026_04April_shift1.json",
      "count": 75
    },
    {
      "file": "pyq/jee_main/jee_chemistry_bank.json",
      "count": 5501
    },
    {
      "file": "pyq/jee_main/jee_maths_bank.json",
      "count": 5456
    },
    {
      "file": "pyq/jee_main/jee_physics_bank.json",
      "count": 287
    },
    {
      "file": "pyq/neet/neet_biology_bank.json",
      "count": 5000
    },
    {
      "file": "pyq/normalized/jee_main_normalized.json",
      "count": 300
    },
    {
      "file": "pyq/other/general_aptitude_bank.json",
      "count": 5068
    },
    {
      "file": "pyq/processed/jee_main_1784396213243.json",
      "count": 299
    },
    {
      "file": "pyq/processed/jee_main_complete.json",
      "count": 486
    },
    {
      "file": "pyq/processed/jee_pyq_papers.json",
      "count": 299
    }
  ]
}